aocstat/__init__.py
aocstat/api.py
aocstat/config.py
aocstat/format.py
aocstat/main.py
aocstat-0.2.4.dist-info/LICENSE
aocstat-0.2.4.dist-info/METADATA
aocstat-0.2.4.dist-info/WHEEL
aocstat-0.2.4.dist-info/entry_points.txt
aocstat-0.2.4.dist-info/RECORD
